{
  "datasets": [
    {
      "name": "054b5cae",
      "displayName": "vw_fact_orders_enriched",
      "queryLines": [
        "SELECT * FROM fmcg.gold.vw_fact_orders_enriched"
      ]
    }
  ],
  "pages": [
    {
      "name": "6772a40a",
      "displayName": "Summery",
      "layout": [
        {
          "widget": {
            "name": "monthly-sales-trend",
            "queries": [
              {
                "name": "main_query",
                "query": {
                  "datasetName": "054b5cae",
                  "fields": [
                    {
                      "name": "monthly(date)",
                      "expression": "DATE_TRUNC(\"MONTH\", `date`)"
                    },
                    {
                      "name": "sum(total_amount_inr)",
                      "expression": "SUM(`total_amount_inr`)"
                    }
                  ],
                  "disaggregated": false
                }
              }
            ],
            "spec": {
              "version": 3,
              "widgetType": "line",
              "encodings": {
                "x": {
                  "fieldName": "monthly(date)",
                  "scale": {
                    "type": "temporal"
                  }
                },
                "y": {
                  "fieldName": "sum(total_amount_inr)",
                  "scale": {
                    "type": "quantitative"
                  }
                }
              },
              "frame": {
                "title": "Monthly Sales Trend",
                "showTitle": true
              }
            }
          },
          "position": {
            "x": 0,
            "y": 1,
            "width": 3,
            "height": 6
          }
        },
        {
          "widget": {
            "name": "d4e4411e",
            "multilineTextboxSpec": {
              "lines": [
                "# <span style=\"text-align:center;display:block\"><span style=\"font-size: 30px;font-family: Georgia;color: #077A9D;\">FMCG Sales Analytics Report</span></span>"
              ]
            },
            "specExtensions": {
              "widgetBorderColor": {
                "dark": "#08F31E"
              }
            }
          },
          "position": {
            "x": 0,
            "y": 0,
            "width": 6,
            "height": 1
          }
        },
        {
          "widget": {
            "name": "sales-by-division",
            "queries": [
              {
                "name": "main_query",
                "query": {
                  "datasetName": "054b5cae",
                  "fields": [
                    {
                      "name": "sum(total_amount_inr)",
                      "expression": "SUM(`total_amount_inr`)"
                    },
                    {
                      "name": "quarter",
                      "expression": "`quarter`"
                    }
                  ],
                  "disaggregated": false
                }
              }
            ],
            "spec": {
              "version": 3,
              "widgetType": "pie",
              "encodings": {
                "angle": {
                  "fieldName": "sum(total_amount_inr)",
                  "scale": {
                    "type": "quantitative"
                  }
                },
                "color": {
                  "fieldName": "quarter",
                  "scale": {
                    "type": "categorical"
                  }
                },
                "label": {
                  "show": true
                }
              },
              "frame": {
                "title": "  Sales by Quarter",
                "showTitle": true
              }
            }
          },
          "position": {
            "x": 0,
            "y": 7,
            "width": 3,
            "height": 6
          }
        },
        {
          "widget": {
            "name": "total-sales-amount",
            "queries": [
              {
                "name": "main_query",
                "query": {
                  "datasetName": "054b5cae",
                  "fields": [
                    {
                      "name": "sum(total_amount_inr)",
                      "expression": "SUM(`total_amount_inr`)"
                    }
                  ],
                  "disaggregated": false
                }
              }
            ],
            "spec": {
              "version": 2,
              "widgetType": "counter",
              "encodings": {
                "value": {
                  "fieldName": "sum(total_amount_inr)"
                }
              },
              "frame": {
                "title": "Total Sales Amount",
                "showTitle": true
              }
            }
          },
          "position": {
            "x": 3,
            "y": 1,
            "width": 1,
            "height": 2
          }
        },
        {
          "widget": {
            "name": "09ef2cc3",
            "queries": [
              {
                "name": "main_query",
                "query": {
                  "datasetName": "054b5cae",
                  "fields": [
                    {
                      "name": "countdistinct(product_code)",
                      "expression": "COUNT(DISTINCT `product_code`)"
                    }
                  ],
                  "disaggregated": false
                }
              }
            ],
            "spec": {
              "version": 2,
              "widgetType": "counter",
              "encodings": {
                "value": {
                  "fieldName": "countdistinct(product_code)"
                }
              },
              "frame": {
                "title": "Total Products",
                "showTitle": true,
                "showDescription": false
              }
            }
          },
          "position": {
            "x": 4,
            "y": 1,
            "width": 1,
            "height": 2
          }
        },
        {
          "widget": {
            "name": "e3c70ead",
            "queries": [
              {
                "name": "main_query",
                "query": {
                  "datasetName": "054b5cae",
                  "fields": [
                    {
                      "name": "countdistinct(customer_code)",
                      "expression": "COUNT(DISTINCT `customer_code`)"
                    }
                  ],
                  "disaggregated": false
                }
              }
            ],
            "spec": {
              "version": 2,
              "widgetType": "counter",
              "encodings": {
                "value": {
                  "fieldName": "countdistinct(customer_code)"
                }
              },
              "frame": {
                "title": "Total Customers",
                "showTitle": true
              }
            }
          },
          "position": {
            "x": 5,
            "y": 1,
            "width": 1,
            "height": 2
          }
        },
        {
          "widget": {
            "name": "sales-by-category-1",
            "queries": [
              {
                "name": "main_query",
                "query": {
                  "datasetName": "054b5cae",
                  "fields": [
                    {
                      "name": "platform",
                      "expression": "`platform`"
                    },
                    {
                      "name": "sum(total_amount_inr)",
                      "expression": "SUM(`total_amount_inr`)"
                    }
                  ],
                  "disaggregated": false
                }
              }
            ],
            "spec": {
              "version": 3,
              "widgetType": "bar",
              "encodings": {
                "x": {
                  "fieldName": "platform",
                  "scale": {
                    "type": "categorical",
                    "sort": {
                      "by": "y-reversed"
                    }
                  }
                },
                "y": {
                  "fieldName": "sum(total_amount_inr)",
                  "scale": {
                    "type": "quantitative"
                  }
                },
                "color": {
                  "fieldName": "platform",
                  "scale": {
                    "type": "categorical"
                  }
                }
              },
              "frame": {
                "title": "Sales by Platform",
                "showTitle": true
              }
            }
          },
          "position": {
            "x": 3,
            "y": 3,
            "width": 3,
            "height": 4
          }
        },
        {
          "widget": {
            "name": "sales-category",
            "queries": [
              {
                "name": "main_query",
                "query": {
                  "datasetName": "054b5cae",
                  "fields": [
                    {
                      "name": "sum(total_amount_inr)",
                      "expression": "SUM(`total_amount_inr`)"
                    },
                    {
                      "name": "category",
                      "expression": "`category`"
                    }
                  ],
                  "disaggregated": false
                }
              }
            ],
            "spec": {
              "version": 3,
              "widgetType": "heatmap",
              "encodings": {
                "y": {
                  "fieldName": "category",
                  "scale": {
                    "type": "categorical"
                  }
                },
                "color": {
                  "fieldName": "sum(total_amount_inr)",
                  "scale": {
                    "type": "quantitative"
                  }
                }
              },
              "frame": {
                "title": "Sales by Category",
                "showTitle": true
              }
            }
          },
          "position": {
            "x": 3,
            "y": 7,
            "width": 3,
            "height": 6
          }
        }
      ],
      "pageType": "PAGE_TYPE_CANVAS"
    },
    {
      "name": "9a661e76",
      "displayName": "Global Filters",
      "layout": [
        {
          "widget": {
            "name": "7f3ec687",
            "spec": {
              "version": 2,
              "widgetType": "filter-single-select",
              "encodings": {},
              "frame": {
                "showTitle": true
              }
            }
          },
          "position": {
            "x": 0,
            "y": 0,
            "width": 1,
            "height": 2
          }
        }
      ],
      "pageType": "PAGE_TYPE_GLOBAL_FILTERS"
    }
  ],
  "uiSettings": {
    "theme": {
      "widgetHeaderAlignment": "ALIGNMENT_UNSPECIFIED"
    },
    "applyModeEnabled": false
  }
}
